tffs/__init__.py
tffs/app.py
tffs-1.1.2.dist-info/LICENSE
tffs-1.1.2.dist-info/METADATA
tffs-1.1.2.dist-info/WHEEL
tffs-1.1.2.dist-info/top_level.txt
tffs-1.1.2.dist-info/RECORD
