Metadata-Version: 2.2
Name: tffs
Version: 1.1.2
Summary: Feature selection based on top frequency
Home-page: https://github.com/VuKieuAnh/pypi-tffs
Author: Vu Kieu Anh
Author-email: vukieuanh.hnue@gmail.com
Classifier: Programming Language :: Python :: 3
Classifier: License :: OSI Approved :: MIT License
Classifier: Operating System :: OS Independent
Requires-Python: >=3.6
License-File: LICENSE
Requires-Dist: numpy>=1.21.0
Requires-Dist: scikit-learn>=1.0.2
Dynamic: author
Dynamic: author-email
Dynamic: classifier
Dynamic: description
Dynamic: description-content-type
Dynamic: home-page
Dynamic: requires-dist
Dynamic: requires-python
Dynamic: summary
